kurby/__init__.py
kurby/api.py
kurby/cli.py
kurby/constants.py
kurby/decrypt.py
kurby/exceptions.py
kurby/helpers.py
kurby/messages.py
kurby/schemas.py
kurby/utils.py
kurby-0.3.3.dist-info/entry_points.txt
kurby-0.3.3.dist-info/LICENSE
kurby-0.3.3.dist-info/WHEEL
kurby-0.3.3.dist-info/METADATA
kurby-0.3.3.dist-info/RECORD
