Metadata-Version: 2.1
Name: kurby
Version: 0.3.3
Summary: A modern CLI to download animes automatically from Twist.moe
Home-page: https://github.com/aberrier/kurby
License: BSD-2-Clause
Author: Alain BERRIER
Author-email: alain.berrier@outlook.com
Maintainer: Alain BERRIER
Maintainer-email: alain.berrier@outlook.com
Requires-Python: >=3.7,<4.0
Classifier: Development Status :: 4 - Beta
Classifier: Environment :: Console
Classifier: Intended Audience :: Developers
Classifier: Intended Audience :: End Users/Desktop
Classifier: License :: OSI Approved :: BSD License
Classifier: Operating System :: OS Independent
Classifier: Programming Language :: Python :: 3
Classifier: Programming Language :: Python :: 3.7
Classifier: Programming Language :: Python :: 3.8
Classifier: Programming Language :: Python :: 3.9
Classifier: Topic :: Education
Classifier: Topic :: Internet
Classifier: Topic :: Software Development :: Libraries
Classifier: Typing :: Typed
Requires-Dist: Faker (>=5,<6)
Requires-Dist: Js2Py (>=0,<1)
Requires-Dist: PyInquirer (>=1.0.3,<2.0.0)
Requires-Dist: arrow (>=0.17,<0.18)
Requires-Dist: fuzzywuzzy (>=0,<1)
Requires-Dist: httpx (>=0,<1)
Requires-Dist: pycryptodomex (>=3.9,<4.0)
Requires-Dist: pydantic (>=1.7,<2.0)
Requires-Dist: tenacity (>=6,<7)
Requires-Dist: tqdm (>=4,<5)
Requires-Dist: typer (>=0,<1)
Requires-Dist: typer-cli (>=0,<1)
Project-URL: Documentation, https://github.com/aberrier/kurby
Project-URL: Repository, https://github.com/aberrier/kurby
